bmhub/__init__.py
bmhub/backend.py
bmhub/hf_hub.py
bmhub/ms_hub.py
bmhub/schema.py
bmhub/utils.py
bmhub-1.0.0.dist-info/METADATA
bmhub-1.0.0.dist-info/WHEEL
bmhub-1.0.0.dist-info/entry_points.txt
bmhub-1.0.0.dist-info/licenses/LICENSE
bmhub-1.0.0.dist-info/RECORD
