Metadata-Version: 2.4
Name: bmhub
Version: 1.0.0
Summary: 增强从 Hugging Face Hub 与 ModelScope Hub 下载新模型与列出、更新、删除已下载模型的体验
Project-URL: Homepage, https://github.com/yansh97/bmhub
Author-email: YanSH <yansh97@foxmail.com>
License: MIT License
License-File: LICENSE
Requires-Python: >=3.12
Requires-Dist: huggingface-hub>=0.33.2
Requires-Dist: modelscope>=1.27.1
Requires-Dist: pydantic>=2.11.7
Requires-Dist: rich>=14.0.0
Requires-Dist: typer>=0.16.0
